forgetnet/__init__.py
forgetnet/core.py
forgetnet/dpweights.py
forgetnet/privacy_engine.py
forgetnet/trainer.py
forgetnet/dp/__init__.py
forgetnet/dp/dp_shuffle.py
forgetnet/dp/membership_inference.py
forgetnet-0.1.21.dist-info/LICENSE
forgetnet-0.1.21.dist-info/METADATA
forgetnet-0.1.21.dist-info/WHEEL
forgetnet-0.1.21.dist-info/entry_points.txt
forgetnet-0.1.21.dist-info/top_level.txt
forgetnet-0.1.21.dist-info/RECORD
